txgsm/__init__.py
txgsm/protocol.py
txgsm/service.py
txgsm/utils.py
txgsm/tests/__init__.py
txgsm/tests/base.py
txgsm/tests/test_protocol.py
txgsm/tests/test_service.py
txgsm/tests/test_utils.py
twisted/plugins/txgsm_plugin.py
txgsm-0.2.0.dist-info/top_level.txt
txgsm-0.2.0.dist-info/METADATA
txgsm-0.2.0.dist-info/DESCRIPTION.rst
txgsm-0.2.0.dist-info/metadata.json
txgsm-0.2.0.dist-info/WHEEL
txgsm-0.2.0.dist-info/RECORD
