Metadata-Version: 2.0
Name: txgsm
Version: 0.2.0
Summary: Utilities for talking to a GSM modem over USB via AT commands.
Home-page: http://github.com/smn/txgsm
Author: Simon de Haan
Author-email: simon@praekeltfoundation.org
License: BSD
Platform: UNKNOWN
Classifier: Development Status :: 3 - Alpha
Classifier: Intended Audience :: Developers
Classifier: License :: OSI Approved :: BSD License
Classifier: Operating System :: POSIX
Classifier: Programming Language :: Python
Classifier: Topic :: Software Development :: Libraries :: Python Modules
Classifier: Topic :: System :: Networking
Classifier: Framework :: Twisted
Requires-Dist: Twisted
Requires-Dist: pyserial
Requires-Dist: mock
